vodafone_ie_account_checker/__init__.py
vodafone_ie_account_checker/api.py
vodafone_ie_account_checker-1.0.7.dist-info/AUTHORS.rst
vodafone_ie_account_checker-1.0.7.dist-info/LICENSE
vodafone_ie_account_checker-1.0.7.dist-info/METADATA
vodafone_ie_account_checker-1.0.7.dist-info/WHEEL
vodafone_ie_account_checker-1.0.7.dist-info/top_level.txt
vodafone_ie_account_checker-1.0.7.dist-info/RECORD
