Metadata-Version: 2.1
Name: vodafone-ie-account-checker
Version: 1.0.7
Summary: Python package to check broadband usage data from vodafone.ie
Home-page: https://github.com/fbradyirl/vodafone_ie_account_checker
Author: Finbarr Brady
Author-email: finbarr.brady@gmail.com
License: MIT license
Keywords: vodafone_ie_account_checker
Platform: UNKNOWN
Classifier: Development Status :: 2 - Pre-Alpha
Classifier: Intended Audience :: Developers
Classifier: License :: OSI Approved :: MIT License
Classifier: Natural Language :: English
Classifier: Programming Language :: Python :: 3
Classifier: Programming Language :: Python :: 3.7
Classifier: Programming Language :: Python :: 3.8
Requires-Python: >=3.7
Requires-Dist: requests (>=2.23.0)
Requires-Dist: lxml (>=4.5.0)
Requires-Dist: coloredlogs (>=14.0)
